LICENSE.txt
README.md
setup.cfg
setup.py
callpyback/__init__.py
callpyback/callpyback.py
callpyback/utils.py
callpyback.egg-info/PKG-INFO
callpyback.egg-info/SOURCES.txt
callpyback.egg-info/dependency_links.txt
callpyback.egg-info/top_level.txt
callpyback/mixins/__init__.py
callpyback/mixins/base.py
callpyback/mixins/extended.py
tests/__init__.py
tests/test_callpyback.py
tests/test_utils.py
tests/mixins/__init__.py
tests/mixins/test_base.py
tests/mixins/test_extended.py