Metadata-Version: 2.1
Name: callpyback
Version: 1.2.0
Summary: Simple and readable Pure Python callbacks!
Home-page: https://github.com/samuelgregorovic/callpyback
Author: samuelgregorovic
Author-email: samuelgregorovic@gmail.com
License: UNKNOWN
Download-URL: https://github.com/samuelgregorovic/callpyback/archive/refs/tags/v.1.2.0.tar.gz
Keywords: callpyback,callback,python,pure,pythonic,background
Platform: UNKNOWN
License-File: LICENSE.txt
